{
  "timeZone": "America/New_York",
  "dependencies": {
    "enabledAdvancedServices": []
  },
  "exceptionLogging": "STACKDRIVER",
  "runtimeVersion": "V8",
  "webapp": {
    "executeAs": "USER_ACCESSING",
    "access": "ANYONE"
  },
  "oauthScopes": [
    "https://www.googleapis.com/auth/spreadsheets.currentonly",
    "https://www.googleapis.com/auth/script.container.ui",
    "https://www.googleapis.com/auth/script.scriptapp",
    "https://www.googleapis.com/auth/userinfo.email",
    "https://www.googleapis.com/auth/script.external_request",
    "https://www.googleapis.com/auth/userinfo.profile",
    "https://www.googleapis.com/auth/script.send_mail"
  ],
  "urlFetchWhitelist": [
    "https://*.pipedrive.com/",
    "https://pipedrive-sheets.vercel.app/",
    "https://*.vercel.app/"
  ],
  "addOns": {
    "common": {
      "name": "PipedriveSheets",
      "logoUrl": "https://pipedrive-sheets.vercel.app/logo.png",
      "universalActions": [{
        "label": "Open Pipedrive Sync",
        "runFunction": "onOpen"
      }]
    },
    "sheets": {
      "homepageTrigger": {
        "runFunction": "onOpen"
      }
    }
  }
}